{
	"code": "mmx-image-gallery",
	"name": "MMX Image Gallery",
	"type": "library",
	"version": "26.01.01",
	"managed": true,
	"resourcegroup_code": "mmx-image-gallery",
	"scripts": [
		{
			"filepath": "src/js/mmx-image-gallery.js",
			"resource_code": "mmx-image-gallery",
			"attributes": [
				{
					"name": "type",
					"value": "text/javascript"
				},
				{
					"name": "integrity",
					"value": "sha256-8t5ghcCEqJ0/eVMxzkttU06AJ3Y6FT5++3eidt9KpqU= sha384-oURg1e8O3rKQ+I1k4U65o1dHRFGld75hcF6ptSDgr+n95SpCBvW3ZIayFD0Hmxie sha512-Pj+nAcShpnWU5b/g+aoj6w/ap5LYFSk+t/8DrcUYJ7UCMoWrpqsFLXHjlwUSACEj3IslEt0onfPsJh52DdpDiQ=="
				},
				{
					"name": "crossorigin",
					"value": "anonymous"
				}
			]
		}
	],
	"styles": [
		{
			"filepath": "src/css/mmx-image-gallery.css",
			"resource_code": "mmx-image-gallery",
			"attributes": [
				{
					"name": "type",
					"value": "text/css"
				},
				{
					"name": "media",
					"value": "all"
				},
				{
					"name": "rel",
					"value": "stylesheet"
				},
				{
					"name": "integrity",
					"value": "sha256-VugstqHIwIuiryGT1DF4EHxb4srr/VVFe8vZUboUlqM= sha384-UmnQVcAtRqtDPFYh/RYXjGnqT0Uag7MdPLQskIU5Ftn+RwveHeoLkkFVZREMEFPH sha512-pZ3Fgn+m0AKYTNcHWDguDUm8NPpUVHs3ITxfMYD7C0DavOpOKeQXNfcb7MLYAblFPqMwq75HtXkHLGCHHtz6og=="
				},
				{
					"name": "crossorigin",
					"value": "anonymous"
				}
			]
		}
	],
	"depends": {
		"mmx-base": "=26.01.01",
		"mmx-hero": "=26.01.01",
		"mmx-hero-slider": "=26.01.01"
	}
}