{
    "code": "mmx-text",
    "type": "Z",
    "is_global": false,
    "active": true,
    "attributes": [
        {
            "name": "type",
            "value": "text/css"
        },
        {
            "name": "media",
            "value": "all"
        },
        {
            "name": "rel",
            "value": "stylesheet"
        },
        {
            "name": "integrity",
            "value": "sha256-vNHpWOGTPqTd4TXu/oDn/ZKRm7gf0RGU4J5qbVioz1E= sha384-ZlfWt8Mfu+vN20PDEIFCwPBbmT6OI7CMXFQ0dJhFm7Dftxf0YIxsHPyqC3iBzH8Y sha512-OurVUTqczEOeoybQPSn5YEGbrIToyPuZi1BuwflAi1H4HnoGoO+jnHZB/WDHfiGCd1Hn7RjSLVayz2WxGRQCQw=="
        },
        {
            "name": "crossorigin",
            "value": "anonymous"
        }
    ],
    "linked_pages": []
}