{
    "code": "mmx-card",
    "type": "Z",
    "is_global": false,
    "active": true,
    "attributes": [
        {
            "name": "type",
            "value": "text/css"
        },
        {
            "name": "media",
            "value": "all"
        },
        {
            "name": "rel",
            "value": "stylesheet"
        },
        {
            "name": "integrity",
            "value": "sha256-rtzdFULtzvjpJ4Jd1wQABZ7yvzDgqmFKgjkj3UsH0yM= sha384-x//9vC76OnT2bWG/q5QEXLXUkzM0cI7z//01M29WWGUFlpK9m7Ff9nlALK9G9/BL sha512-58V+BGrYZSV/6hYacDtOnME2wR1tvD0K/CVugEIzmrA9Fwt/P3wAAl8ECSsojYKTYtVnL1LXIn8eT9u8Iou1og=="
        },
        {
            "name": "crossorigin",
            "value": "anonymous"
        }
    ],
    "linked_pages": []
}