{
    "items": [
        {
            ".branch_data": {
                "1": {
                    "link": "<a href=\"https://local.coolcommerce.net/mm5/merchant.mvc?Screen=ABUS\" target=\"_self\">About Us</a>",
                    "url": "https://local.coolcommerce.net/mm5/merchant.mvc?Screen=ABUS"
                }
            },
            "active": 1,
            "id": "",
            "link_dest": "ABUS",
            "link_targ": "_self",
            "link_type": "G",
            "name": "About Us"
        },
        {
            ".branch_data": {
                "1": {
                    "link": "<a href=\"https://local.coolcommerce.net/mm5/merchant.mvc?Screen=ACLN\" target=\"_self\">Account</a>",
                    "url": "https://local.coolcommerce.net/mm5/merchant.mvc?Screen=ACLN"
                }
            },
            "active": 1,
            "id": "",
            "link_dest": "ACLN",
            "link_targ": "_self",
            "link_type": "G",
            "name": "Account"
        },
        {
            ".branch_data": {
                "1": {
                    "link": "<a href=\"https://local.coolcommerce.net/mm5/merchant.mvc?Screen=CTUS\" target=\"_self\">Contact Us</a>",
                    "url": "https://local.coolcommerce.net/mm5/merchant.mvc?Screen=CTUS"
                }
            },
            "active": 1,
            "id": "",
            "link_dest": "CTUS",
            "link_targ": "_self",
            "link_type": "G",
            "name": "Contact Us"
        },
        {
            ".branch_data": {
                "1": {
                    "link": "<a href=\"https://local.coolcommerce.net/mm5/merchant.mvc?Screen=FAQS\" target=\"_self\">FAQS</a>",
                    "url": "https://local.coolcommerce.net/mm5/merchant.mvc?Screen=FAQS"
                }
            },
            "active": 1,
            "id": "",
            "link_dest": "FAQS",
            "link_targ": "_self",
            "link_type": "G",
            "name": "FAQS"
        },
        {
            ".branch_data": {
                "1": {
                    "link": "<a href=\"https://local.coolcommerce.net/mm5/merchant.mvc?Screen=ORDH\" target=\"_self\">Order Status</a>",
                    "url": "https://local.coolcommerce.net/mm5/merchant.mvc?Screen=ORDH"
                }
            },
            "active": 1,
            "id": "",
            "link_dest": "ORDH",
            "link_targ": "_self",
            "link_type": "G",
            "name": "Order Status"
        },
        {
            ".branch_data": {
                "1": {
                    "link": "<a href=\"https://local.coolcommerce.net/mm5/merchant.mvc?Screen=WLST\" target=\"_self\">Wish Lists</a>",
                    "url": "https://local.coolcommerce.net/mm5/merchant.mvc?Screen=WLST"
                }
            },
            "active": 1,
            "id": "",
            "link_dest": "WLST",
            "link_targ": "_self",
            "link_type": "G",
            "name": "Wish Lists"
        },
        {
            ".branch_data": {
                "1": {
                    "link": "<a href=\"https://local.coolcommerce.net/mm5/merchant.mvc?Screen=PRPO\" target=\"_self\">Privacy Policy</a>",
                    "url": "https://local.coolcommerce.net/mm5/merchant.mvc?Screen=PRPO"
                }
            },
            "active": 1,
            "id": "",
            "link_dest": "PRPO",
            "link_targ": "_self",
            "link_type": "G",
            "name": "Privacy Policy"
        },
        {
            ".branch_data": {
                "1": {
                    "link": "<a href=\"https://local.coolcommerce.net/mm5/merchant.mvc?Screen=SARP\" target=\"_self\">Shipping &amp;amp; Returns</a>",
                    "url": "https://local.coolcommerce.net/mm5/merchant.mvc?Screen=SARP"
                }
            },
            "active": 1,
            "id": "",
            "link_dest": "SARP",
            "link_targ": "_self",
            "link_type": "G",
            "name": "Shipping &amp; Returns"
        },
        {
            ".branch_data": {
                "1": {
                    "link": "<a href=\"https://local.coolcommerce.net/mm5/merchant.mvc?Screen=SMAP\" target=\"_self\">Site Map</a>",
                    "url": "https://local.coolcommerce.net/mm5/merchant.mvc?Screen=SMAP"
                }
            },
            "active": 1,
            "id": "",
            "link_dest": "SMAP",
            "link_targ": "_self",
            "link_type": "G",
            "name": "Site Map"
        }
    ],
    "layout": "S",
    "name": "Global Footer Quick Links"
}